nbtutor/__init__.py
nbtutor/version.py
nbtutor/ipython/__init__.py
nbtutor/ipython/debugger.py
nbtutor/ipython/magic.py
nbtutor/ipython/constants/__init__.py
nbtutor/ipython/constants/ignore.py
nbtutor/ipython/constants/types.py
nbtutor/ipython/factories/__init__.py
nbtutor/ipython/factories/base_heap_object_factory.py
nbtutor/ipython/factories/basic_heap_object_factory.py
nbtutor/ipython/factories/class_heap_object_factory.py
nbtutor/ipython/factories/heap_object_factory.py
nbtutor/ipython/factories/instance_heap_object_factory.py
nbtutor/ipython/factories/kvp_heap_object_factory.py
nbtutor/ipython/factories/named_heap_object_factory.py
nbtutor/ipython/factories/sequence_heap_object_factory.py
nbtutor/ipython/factories/stack_frame_factory.py
nbtutor/ipython/factories/trace_step_factory.py
nbtutor/ipython/factories/unknown_heap_object_factory.py
nbtutor/ipython/helpers/__init__.py
nbtutor/ipython/helpers/dictionary.py
nbtutor/ipython/helpers/object.py
nbtutor/ipython/helpers/output.py
nbtutor/ipython/models/__init__.py
nbtutor/ipython/models/heap_object.py
nbtutor/ipython/models/options.py
nbtutor/ipython/models/serializable.py
nbtutor/ipython/models/stack.py
nbtutor/ipython/models/stack_frame.py
nbtutor/ipython/models/trace_step.py
nbtutor/ipython/models/types.py
nbtutor/ipython/models/unique_identifier.py
nbtutor/ipython/models/variable.py
nbtutor/static/nbtutor.min.css
nbtutor/static/nbtutor.min.js
nbtutor/static/nbtutor.notebook.js
nbtutor-2.0.3.dist-info/LICENCE.md
nbtutor-2.0.3.dist-info/METADATA
nbtutor-2.0.3.dist-info/WHEEL
nbtutor-2.0.3.dist-info/top_level.txt
nbtutor-2.0.3.dist-info/RECORD
