Metadata-Version: 2.1
Name: nbtutor
Version: 2.0.3
Summary: Visualize Python code execution in Jupyter Notebook cells
Home-page: https://github.com/lgpage/nbtutor
Author: Logan Page
Author-email: page.lg@gmail.com
License: BSD 3-Clause
Keywords: ipython jupyter notebook python tutor visualize code execution
Platform: UNKNOWN
Classifier: Development Status :: 5 - Production/Stable
Classifier: Framework :: IPython
Classifier: Programming Language :: Python
Classifier: License :: OSI Approved :: BSD License
License-File: LICENCE.md
Requires-Dist: notebook
